Communication_System/Ask/AskDemod/AskDemod.srcs/sources_1/new/FreqDiv.v
`timescale 1ns / 1ps
//////////////////////////////////////////////////////////////////////////////////
// Company: 
// Engineer: 
// 
// Create Date: 06/13/2025 08:48:45 PM
// Design Name: 
// Module Name: FreqDiv
// Project Name: 
// Target Devices: 
// Tool Versions: 
// Description: 
// 
// Dependencies: 
// 
// Revision:
// Revision 0.01 - File Created
// Additional Comments:
// 
//////////////////////////////////////////////////////////////////////////////////


module FreqDiv(
    rst,clk4,clk_in,clk_I,clk_Q
    );
    input rst,clk4,clk_in;
    output clk_I,clk_Q;
    
    reg [3:0]count;
    reg clk_I_reg,clk_Q_reg;
    
    always@(posedge clk4 or posedge rst)begin
        if(rst)begin
            count <= 3'd0;
            clk_I_reg <= 1'd0;
            clk_Q_reg <= 1'd0;
        end
        else begin
            if(clk_in)
                count <= count + 1'd1;
            clk_I_reg <= ~count[2];
            clk_Q_reg <= count[2];
        end
    end
    
    assign clk_I = clk_I_reg;
    assign clk_Q = clk_Q_reg;
endmodule

Communication_System/Ask/AskDemod/AskDemod.srcs/sources_1/new/monostable.v
`timescale 1ns / 1ps
//////////////////////////////////////////////////////////////////////////////////
// Company: 
// Engineer: 
// 
// Create Date: 06/18/2025 08:06:04 PM
// Design Name: 
// Module Name: monostable
// Project Name: 
// Target Devices: 
// Tool Versions: 
// Description: 
// 
// Dependencies: 
// 
// Revision:
// Revision 0.01 - File Created
// Additional Comments:
// 
//////////////////////////////////////////////////////////////////////////////////


module monostable(
    rst,clk4,din,dout
    );
    input rst,clk4,din;
    output dout;
    
    reg reg_dout,start;
    reg [1:0]count;
    
    always@(posedge clk4 or posedge rst)begin
        if(rst)begin
            count <= 2'd0;
            reg_dout <= 1'd0;
            start <= 1'd0;
        end
        else begin
            if(din==1'd1)begin
                start <= 1'd1;
                reg_dout <= 1'd1;
            end
            if(start == 1'd1)begin
                reg_dout <= 1'd1;
                if(count < 2'd3)
                    count <= count + 1'd1;
                else
                    start <= 1'd0;
            end
            else begin
                count <= 2'd0;
                reg_dout <= 1'd0;
            end
        end     
    end
    assign dout = reg_dout;
endmodule

Communication_System/Ask/AskDemod/AskDemod.srcs/sources_1/new/Control.v
`timescale 1ns / 1ps
//////////////////////////////////////////////////////////////////////////////////
// Company: 
// Engineer: 
// 
// Create Date: 06/18/2025 07:52:13 PM
// Design Name: 
// Module Name: Control
// Project Name: 
// Target Devices: 
// Tool Versions: 
// Description: 
// 
// Dependencies: 
// 
// Revision:
// Revision 0.01 - File Created
// Additional Comments:
// 
//////////////////////////////////////////////////////////////////////////////////


module Control(
    rst,clk4,pd_bef,pd_aft,clk_d1,clk_d2,clk_in
    );
    input rst,clk4,pd_bef,pd_aft,clk_d1,clk_d2;
    output clk_in;
    
    wire un1_gate_open,gate_open,gate_close,clk_in;
    
    monostable u1(
    .rst(rst),
    .clk4(clk4),
    .din(pd_bef),
    .dout(un1_gate_open)
    );
    
    monostable u2(
    .rst(rst),
    .clk4(clk4),
    .din(pd_aft),
    .dout(gate_close)
    );
    
    assign gate_open = ~un1_gate_open;
    assign clk_in = (gate_open&clk_d1)|(gate_close&clk_d2);
endmodule

Communication_System/Ask/AskDemod/AskDemod.srcs/sources_1/new/ClkTrans.v
`timescale 1ns / 1ps
//////////////////////////////////////////////////////////////////////////////////
// Company: 
// Engineer: 
// 
// Create Date: 06/13/2025 08:48:45 PM
// Design Name: 
// Module Name: ClkTrans
// Project Name: 
// Target Devices: 
// Tool Versions: 
// Description: 
// 
// Dependencies: 
// 
// Revision:
// Revision 0.01 - File Created
// Additional Comments:
// 
//////////////////////////////////////////////////////////////////////////////////


module ClkTrans(
    rst,clk4,clk_d1,clk_d2
    );
    input rst,clk4;
    output clk_d1,clk_d2;
    
    reg [1:0] count;
    
    always@(posedge clk4 or posedge rst)begin
        if(rst)
            count <= 2'd0;
        else
            count <= count + 2'd1;
    end
    
    assign clk_d1 = (count == 2'd0)?1'd1:1'd0;
    assign clk_d2 = (count == 2'd2)?1'd1:1'd0;
endmodule

Communication_System/Ask/AskDemod/AskDemod.srcs/sources_1/new/DifferPD.v
`timescale 1ns / 1ps
//////////////////////////////////////////////////////////////////////////////////
// Company: 
// Engineer: 
// 
// Create Date: 06/13/2025 08:48:45 PM
// Design Name: 
// Module Name: DifferPD
// Project Name: 
// Target Devices: 
// Tool Versions: 
// Description: 
// 
// Dependencies: 
// 
// Revision:
// Revision 0.01 - File Created
// Additional Comments:
// 
//////////////////////////////////////////////////////////////////////////////////


module DifferPD(
    rst,clk4,din,clk_I,clk_Q,pd_bef,pd_aft
    );
    input rst,clk4,din,clk_I,clk_Q;
    output pd_bef,pd_aft;
    
//    reg din_d;
//    wire din_edge;
    
//    always@(posedge clk4 or posedge rst)begin
//        if(rst)
//            din_d <= 1'd0;
//        else 
//            din_d <= din;
//    end
    
//    assign din_edge = din_d ^ din;
    
//    assign pd_bef = din_edge & clk_I;
//    assign pd_aft = din_edge & clk_Q;

    reg din_d,din_edge;
    reg pdbef,pdaft;
    always@(posedge clk4 or posedge rst)begin
        if(rst)begin
            din_d <= 1'b0;
            din_edge <= 1'b0;
            pdbef <= 1'b0;
            pdaft <= 1'b0;
        end
        else begin
            din_d <= din;
            din_edge <= din_d ^ din;
            pdbef <= (din_edge & clk_I);
            pdaft <= (din_edge & clk_Q);
        end
    end
    assign pd_bef = pdbef;
    assign pd_aft = pdaft;
endmodule

Communication_System/Ask/AskDemod/AskDemod.srcs/sources_1/new/BitSync.v
`timescale 1ns / 1ps
//////////////////////////////////////////////////////////////////////////////////
// Company: 
// Engineer: 
// 
// Create Date: 06/13/2025 08:40:07 PM
// Design Name: 
// Module Name: BitSync
// Project Name: 
// Target Devices: 
// Tool Versions: 
// Description: 
// 
// Dependencies: 
// 
// Revision:
// Revision 0.01 - File Created
// Additional Comments:
// 
//////////////////////////////////////////////////////////////////////////////////


module BitSync(
    rst,clk4,din,sync
    );
    input rst,clk4,din;
    output sync;
    
    wire clk_Q,pd_bef,pd_aft,clk_d1,clk_d2,clk_in;
    
    DifferPD u1(
    .rst(rst),
    .clk4(clk4),
    .din(din),
    .clk_I(sync),
    .clk_Q(clk_Q),
    .pd_bef(pd_bef),
    .pd_aft(pd_aft)
    );
    
    ClkTrans u2(
    .rst(rst),
    .clk4(clk4),
    .clk_d1(clk_d1),
    .clk_d2(clk_d2)
    );
    
    Control u3(
    .rst(rst),
    .clk4(clk4),
    .pd_bef(pd_bef),
    .pd_aft(pd_aft),
    .clk_d1(clk_d1),
    .clk_d2(clk_d2),
    .clk_in(clk_in)
    );

    FreqDiv u4(
    .rst(rst),
    .clk4(clk4),
    .clk_in(clk_in),
    .clk_I(sync),
    .clk_Q(clk_Q)
    );
endmodule

Communication_System/Ask/AskDemod/AskDemod.srcs/sources_1/new/Gate.v
`timescale 1ns / 1ps
//////////////////////////////////////////////////////////////////////////////////
// Company: 
// Engineer: 
// 
// Create Date: 06/12/2025 09:19:15 PM
// Design Name: 
// Module Name: Gate
// Project Name: 
// Target Devices: 
// Tool Versions: 
// Description: 
// 
// Dependencies: 
// 
// Revision:
// Revision 0.01 - File Created
// Additional Comments:
// 
//////////////////////////////////////////////////////////////////////////////////


module Gate(
    rst,clk,din,mean
    );
    input rst,clk;
    input signed [13:0] din;
    output signed [21:0] mean;
    
    reg [13:0] ShiftReg [255:0];
    integer i,j;
    always@(posedge clk or posedge rst)begin
        if(rst)begin
            for (i=0;i<=255;i=i+1)
                ShiftReg[i] <= 14'd0;
        end
        else begin
            for (j=0;j<=254;j=j+1)
                ShiftReg[j+1] <= ShiftReg[j];
            ShiftReg[0] <= din;
        end
    end
    
    reg signed [21:0] sum;
    always@(posedge clk or posedge rst)begin
        if(rst)
            sum <= 22'd0;
        else
            sum <= sum+{{8{din[13]}},din}-{{8{ShiftReg[255][13]}},ShiftReg[255]};
    end
    assign mean = sum[21:8];
endmodule

Communication_System/Ask/AskDemod/AskDemod.gen/sources_1/ip/lpf/lpf_bmstub.v
// Copyright 1986-2022 Xilinx, Inc. All Rights Reserved.
// Copyright 2022-2025 Advanced Micro Devices, Inc. All Rights Reserved.
// -------------------------------------------------------------------------------

`timescale 1 ps / 1 ps

(* BLOCK_STUB = "true" *)
module lpf (
  aclk,
  s_axis_data_tvalid,
  s_axis_data_tready,
  s_axis_data_tdata,
  m_axis_data_tvalid,
  m_axis_data_tdata
);

  (* X_INTERFACE_INFO = "xilinx.com:signal:clock:1.0 aclk_intf CLK" *)
  (* X_INTERFACE_MODE = "slave aclk_intf" *)
  (* X_INTERFACE_PARAMETER = "XIL_INTERFACENAME aclk_intf, ASSOCIATED_BUSIF S_AXIS_CONFIG:M_AXIS_DATA:S_AXIS_DATA:S_AXIS_RELOAD, ASSOCIATED_RESET aresetn, ASSOCIATED_CLKEN aclken, FREQ_HZ 100000000, FREQ_TOLERANCE_HZ 0, PHASE 0.0, CLK_DOMAIN , ASSOCIATED_PORT , INSERT_VIP 0" *)
  input aclk;
  (* X_INTERFACE_INFO = "xilinx.com:interface:axis:1.0 S_AXIS_DATA TVALID" *)
  (* X_INTERFACE_MODE = "slave S_AXIS_DATA" *)
  (* X_INTERFACE_PARAMETER = "XIL_INTERFACENAME S_AXIS_DATA, TDATA_NUM_BYTES 1, TDEST_WIDTH 0, TID_WIDTH 0, TUSER_WIDTH 0, HAS_TREADY 1, HAS_TSTRB 0, HAS_TKEEP 0, HAS_TLAST 0, FREQ_HZ 100000000, PHASE 0.0, CLK_DOMAIN , LAYERED_METADATA undef, INSERT_VIP 0" *)
  input s_axis_data_tvalid;
  (* X_INTERFACE_INFO = "xilinx.com:interface:axis:1.0 S_AXIS_DATA TREADY" *)
  output s_axis_data_tready;
  (* X_INTERFACE_INFO = "xilinx.com:interface:axis:1.0 S_AXIS_DATA TDATA" *)
  input [7:0]s_axis_data_tdata;
  (* X_INTERFACE_INFO = "xilinx.com:interface:axis:1.0 M_AXIS_DATA TVALID" *)
  (* X_INTERFACE_MODE = "master M_AXIS_DATA" *)
  (* X_INTERFACE_PARAMETER = "XIL_INTERFACENAME M_AXIS_DATA, TDATA_NUM_BYTES 3, TDEST_WIDTH 0, TID_WIDTH 0, TUSER_WIDTH 0, HAS_TREADY 0, HAS_TSTRB 0, HAS_TKEEP 0, HAS_TLAST 0, FREQ_HZ 100000000, PHASE 0.0, CLK_DOMAIN , LAYERED_METADATA undef, INSERT_VIP 0" *)
  output m_axis_data_tvalid;
  (* X_INTERFACE_INFO = "xilinx.com:interface:axis:1.0 M_AXIS_DATA TDATA" *)
  output [23:0]m_axis_data_tdata;

  // stub module has no contents

endmodule

Communication_System/Ask/AskDemod/AskDemod.srcs/sources_1/new/AskDemod.v
`timescale 1ns / 1ps
//////////////////////////////////////////////////////////////////////////////////
// Company: 
// Engineer: 
// 
// Create Date: 06/10/2025 07:26:45 PM
// Design Name: 
// Module Name: AskDemod
// Project Name: 
// Target Devices: 
// Tool Versions: 
// Description: 
// 
// Dependencies: 
// 
// Revision:
// Revision 0.01 - File Created
// Additional Comments:
// 
//////////////////////////////////////////////////////////////////////////////////


module AskDemod(
    clk,rst,din,dout
    );
    input    rst;              //复位信号，高电平有效
	input		clk;   				//FPGA系统时钟:8MHz
	input	 signed [7:0]	din;  //基带输入数据
	output signed [13:0]	dout; //ASK输出数据
	
	reg signed [7:0] abs_din;
	always @(posedge clk or posedge rst)
		if (rst)
			abs_din <= 8'd0;
		else
			if (din[7])
				abs_din <= -din;
			else
			   abs_din <= din;
			   
	wire ast_sink_valid,ast_source_valid,ast_sink_ready;
	wire signed [21:0]  Yout;
	assign ast_sink_valid=1'b1;
	lpf	u0(
		.aclk(clk),
		.s_axis_data_tdata(abs_din),
		.s_axis_data_tvalid(ast_sink_valid),
		.m_axis_data_tdata(Yout),
		.s_axis_data_tready(ast_sink_ready),
		.m_axis_data_tvalid(ast_source_valid));	
	//根据滤波器系数，可知滤波后输出数据最大位宽为输入数据位宽+14位，因此，最高数据位为
	//Yout(21)Yout(21 downto 8)做为输出数据。
	assign dout = Yout[21:8];
endmodule

Communication_System/Ask/AskDemod/AskDemod.srcs/sources_1/new/top.v
`timescale 1ns / 1ps
//////////////////////////////////////////////////////////////////////////////////
// Company: 
// Engineer: 
// 
// Create Date: 06/12/2025 09:49:57 PM
// Design Name: 
// Module Name: top
// Project Name: 
// Target Devices: 
// Tool Versions: 
// Description: 
// 
// Dependencies: 
// 
// Revision:
// Revision 0.01 - File Created
// Additional Comments:
// 
//////////////////////////////////////////////////////////////////////////////////


module top(
    rst,clk,clk4,din,dout,bit_sync
    );
    input rst,clk,clk4;
    input [7:0] din;
    output dout,bit_sync;
    wire signed [13:0] data;
    wire signed [21:0] mean;
    wire judge,sync;
    reg sync_d,dout_reg,bit_sync_reg;
    AskDemod c1(
    .clk(clk),
    .rst(rst),
    .din(din),
    .dout(data)
    );
    
    Gate c2(
    .rst(rst),
    .clk(clk),
    .din(data),
    .mean(mean)
    );
    assign judge = (data<mean)?1'b0:1'b1;
    BitSync c3(
    .clk4(clk4),
    .rst(rst),
    .din(judge),
    .sync(sync)
    );
    
    always@(posedge clk4 or posedge rst)begin
        if(rst)begin
            sync_d <= 1'd0;
            dout_reg <= 1'd0;
        end
        else begin
            sync_d <= sync;
            if(sync_d==1'd1 & sync==1'd0)begin
                dout_reg <= judge;
                bit_sync_reg <= 1'd1;
            end
            else
                bit_sync_reg <= 1'd0;
        end
    end
    assign bit_sync = bit_sync_reg;
    assign dout = dout_reg;
endmodule

Communication_System/Ask/AskDemod/AskDemod.srcs/sim_1/new/tb_AskDemode.v
`timescale 1ns / 1ps

module tb_AskDemode();

    // 测试模块实例化
    reg rst;                    // 复位信号，初始高电平有效
    reg clk;
    reg clk4;                    // 时钟信号
    reg [7:0] din;              // 输入数据
    wire dout;           // 输出数据
    wire bit_sync;
    // 实例化被测模块
//    AskDemod uut (
//        .rst(rst),
//        .clk(clk),
//        .din(din),
//        .dout(dout)
//    );
    top uut (
        .rst(rst),
        .clk(clk),
        .clk4(clk4),
        .din(din),
        .dout(dout),
        .bit_sync(bit_sync)
    );
    
    // 时钟参数定义 - 16MHz (周期62.5ns)
//    parameter CLK_PERIOD = 125; // 单位：ns
//    parameter CLK_PERIOD_plus = 31.25; // 单位：ns
    parameter CLK_PERIOD = 62.5; // 单位：ns
    parameter CLK_PERIOD_plus = 15.625; // 单位：ns
    // 时钟生成
    initial begin
        clk = 0;
        forever #(CLK_PERIOD/2) clk = ~clk;
    end
    
    initial begin
        clk4 = 0;
        forever #(CLK_PERIOD_plus/2) clk4 = ~clk4;
    end
    
    // 复位控制 - 400ns后释放复位
    initial begin
        rst = 1; // 初始复位有效
        #400 rst = 0; // 400ns后释放复位
    end
    
    // 文件读取处理
    integer file_handle;        // 文件句柄
    reg [7:0] file_data [0:9999]; // 存储文件数据的数组
    integer data_count = 0;     // 数据计数器
    integer index = 0;          // 当前读取索引
    reg [7:0] char;             // 用于存储当前字符
    integer i;                  // 循环变量
    integer eof_flag;           // 文件结束标志
    
    initial begin
        // 初始化数组
        for (i = 0; i < 10000; i = i + 1) begin
            file_data[i] = 8'h00;
        end
        
        // 1. 打开文件
        file_handle = $fopen("/home/bryan/workspace/AXU3EG/vivado/AskDemod/ASK2.txt", "r");
        
        if (file_handle == 0) begin
            $display("错误：无法打开文件!");
            $finish;
        end
        
        eof_flag = 0;
        
        // 2. 读取文件内容到数组
        while (!eof_flag) begin
            file_data[data_count] = 8'h00;
            // 逐字符读取8个字符
            for (i = 0; i < 8; i = i + 1) begin
                char = $fgetc(file_handle);
                
                // 检查文件结束
                if ($feof(file_handle)) begin
                    eof_flag = 1;
                end 
                // 处理有效字符
                else if (char == "0" || char == "1") begin
                    file_data[data_count][7-i] = (char == "1") ? 1'b1 : 1'b0;
                    $display("第 %0d 行数据的第 %0d 位为 %s", data_count, i, char);
                end
                else if (char == 10 || char == 13) begin
                    i=i-1;
                end
            end
            
            // 仅当读取到有效数据时才增加计数
            if (i > 0 && !eof_flag) begin
                data_count = data_count + 1;
            end
        end
        
        // 3. 关闭文件
        $fclose(file_handle);
        $display("成功读取 %0d 行数据", data_count);
        
        // 4. 初始化输入
        din = 0;
        
        // 5. 启动数据输入进程
        fork
            begin
                // 等待复位释放
                wait(rst === 0);
                
                // 循环读取数据
                while (index < data_count) begin
                    @(posedge clk);
                    din = file_data[index];
                    index = index + 1;
                end
                
                // 文件结束后保持最后的值
                forever @(posedge clk) din = file_data[data_count-1];
            end
        join
    end  // 修复：添加此end以关闭initial块
    
    // 波形记录
    initial begin
        $dumpfile("askdemod_tb.vcd");
        $dumpvars(0, tb_AskDemode);
    end
    
    // 监控输出
    always @(posedge clk) begin
        if (rst) begin
            $display("Time=%t: 复位中...", $time);
        end else begin
            $display("Time=%t: din=%b, dout=%h", $time, din, dout);
        end
    end
    
    // 仿真结束控制
    initial begin
        #100000; // 仿真运行100us
        $display("仿真完成");
        $finish;
    end

endmodule

Communication_System/Ask/AskDemod/AskDemod.sim/sim_1/behav/xsim/askdemod_tb.vcd
$date
   Tue Jun 24 21:22:39 2025
$end

$version
  2024.2.0
  $dumpfile ("askdemod_tb.vcd") 
$end

$timescale
  1ps
$end

$scope module tb_AskDemode $end
$var reg 1 ! rst $end
$var reg 1 " clk $end
$var reg 1 # clk4 $end
$var reg 8 $ din [7:0] $end
$var wire 1 % dout $end
$var wire 1 & bit_sync $end
$var integer 32 ' file_handle [31:0] $end
$var integer 32 ( data_count [31:0] $end
$var integer 32 ) index [31:0] $end
$var reg 8 * char [7:0] $end
$var integer 32 + i [31:0] $end
$var integer 32 , eof_flag [31:0] $end
$scope module uut $end
$var wire 1 - rst $end
$var wire 1 . clk $end
$var wire 1 / clk4 $end
$var wire 8 0 din [7:0] $end
$var wire 1 % dout $end
$var wire 1 & bit_sync $end
$var wire 14 1 data [13:0] $end
$var wire 22 2 mean [21:0] $end
$var wire 1 3 judge $end
$var wire 1 4 sync $end
$var reg 1 5 sync_d $end
$var reg 1 6 dout_reg $end
$var reg 1 7 bit_sync_reg $end
$scope module c1 $end
$var wire 1 - rst $end
$var wire 1 . clk $end
$var wire 8 0 din [7:0] $end
$var wire 14 1 dout [13:0] $end
$var reg 8 8 abs_din [7:0] $end
$var wire 1 9 ast_sink_valid $end
$var wire 1 : ast_source_valid $end
$var wire 1 ; ast_sink_ready $end
$var wire 22 < Yout [21:0] $end
$scope module u0 $end
$var wire 1 = aclk $end
$var wire 1 > s_axis_data_tvalid $end
$var wire 1 ? s_axis_data_tready $end
$var wire 8 @ s_axis_data_tdata $end
$var wire 1 A m_axis_data_tvalid $end
$var wire 24 B m_axis_data_tdata $end
$upscope $end
$upscope $end
$scope module c2 $end
$var wire 1 - rst $end
$var wire 1 . clk $end
$var wire 14 1 din [13:0] $end
$var wire 22 2 mean [21:0] $end
$var integer 32 C i [31:0] $end
$var integer 32 D j [31:0] $end
$var reg 22 E sum [21:0] $end
$upscope $end
$scope module c3 $end
$var wire 1 - rst $end
$var wire 1 / clk4 $end
$var wire 1 3 din $end
$var wire 1 4 sync $end
$var wire 1 F clk_Q $end
$var wire 1 G pd_bef $end
$var wire 1 H pd_aft $end
$var wire 1 I clk_d1 $end
$var wire 1 J clk_d2 $end
$var wire 1 K clk_in $end
$scope module u1 $end
$var wire 1 - rst $end
$var wire 1 / clk4 $end
$var wire 1 3 din $end
$var wire 1 4 clk_I $end
$var wire 1 F clk_Q $end
$var wire 1 G pd_bef $end
$var wire 1 H pd_aft $end
$var reg 1 L din_d $end
$var reg 1 M din_edge $end
$var reg 1 N pdbef $end
$var reg 1 O pdaft $end
$upscope $end
$scope module u2 $end
$var wire 1 - rst $end
$var wire 1 / clk4 $end
$var wire 1 I clk_d1 $end
$var wire 1 J clk_d2 $end
$var reg 2 P count [1:0] $end
$upscope $end
$scope module u3 $end
$var wire 1 - rst $end
$var wire 1 / clk4 $end
$var wire 1 G pd_bef $end
$var wire 1 H pd_aft $end
$var wire 1 I clk_d1 $end
$var wire 1 J clk_d2 $end
$var wire 1 Q un1_gate_open $end
$var wire 1 R gate_open $end
$var wire 1 S gate_close $end
$var wire 1 K clk_in $end
$scope module u1 $end
$var wire 1 - rst $end
$var wire 1 / clk4 $end
$var wire 1 G din $end
$var wire 1 Q dout $end
$var reg 1 T reg_dout $end
$var reg 1 U start $end
$var reg 2 V count [1:0] $end
$upscope $end
$scope module u2 $end
$var wire 1 - rst $end
$var wire 1 / clk4 $end
$var wire 1 H din $end
$var wire 1 S dout $end
$var reg 1 W reg_dout $end
$var reg 1 X start $end
$var reg 2 Y count [1:0] $end
$upscope $end
$upscope $end
$scope module u4 $end
$var wire 1 - rst $end
$var wire 1 / clk4 $end
$var wire 1 K clk_in $end
$var wire 1 4 clk_I $end
$var wire 1 F clk_Q $end
$var reg 4 Z count [3:0] $end
$var reg 1 [ clk_I_reg $end
$var reg 1 \ clk_Q_reg $end
$upscope $end
$upscope $end
$upscope $end
$upscope $end
$enddefinitions $end

#0
$dumpvars
1!
0"
0#
b0 $
0%
x&
b11111111111111111011000111100000 '
b1111101000000 (
b0 )
b11111111 *
b1000 +
b1 ,
1-
0.
0/
b0 0
b0 1
b0 2
13
04
05
06
x7
b0 8
19
0:
0;
b0 <
0=
1>
0?
b0 @
0A
b0 B
bx C
bx D
b0 E
0F
0G
0H
1I
0J
1K
0L
0M
0N
0O
b0 P
0Q
1R
0S
0T
0U
b0 V
0W
0X
b0 Y
b0 Z
0[
0\
$end

#7813
1#
1/

#15626
0#
0/

#23439
1#
1/

#31250
1"
1.
1;
1=
1?

#31252
0#
0/

#39065
1#
1/

#46878
0#
0/

#54691
1#
1/

#62500
0"
0.
0=

#62504
0#
0/

#70317
1#
1/

#78130
0#
0/

#85943
1#
1/

#93750
1"
1.
1=

#93756
0#
0/

#101569
1#
1/

#109382
0#
0/

#117195
1#
1/

#125000
0"
0.
0=

#125008
0#
0/

#132821
1#
1/

#140634
0#
0/

#148447
1#
1/

#156250
1"
1.
1=

#156260
0#
0/

#164073
1#
1/

#171886
0#
0/

#179699
1#
1/

#187500
0"
0.
0=

#187512
0#
0/

#195325
1#
1/

#203138
0#
0/

#210951
1#
1/

#218750
1"
1.
1=

#218764
0#
0/

#226577
1#
1/

#234390
0#
0/

#242203
1#
1/

#250000
0"
0.
0=

#250016
0#
0/

#257829
1#
1/

#265642
0#
0/

#273455
1#
1/

#281250
1"
1.
1=

#281268
0#
0/

#289081
1#
1/

#296894
0#
0/

#304707
1#
1/

#312500
0"
0.
0=

#312520
0#
0/

#320333
1#
1/

#328146
0#
0/

#335959
1#
1/

#343750
1"
1.
1=

#343772
0#
0/

#351585
1#
1/

#359398
0#
0/

#367211
1#
1/

#375000
0"
0.
0=

#375024
0#
0/

#382837
1#
1/

#390650
0#
0/

#398463
1#
1/

#400000
0!
0-

#406250
1"
b1111111 $
b1 )
1.
b1111111 0
b1111111 8
1=
b1111111 @
b11111111 D

#406276
0#
0/

#414089
1#
0&
1/
14
07
0I
0K
1L
1M
b1 P
b1 Z
1[

#421902
0#
0/

#429715
1#
1/
15
1G
1J
0M
1N
b10 P

#437500
0"
0.
0=

#437528
0#
0/

#445341
1#
1/
0G
0J
0N
b11 P
0T
1U

#453154
0#
0/

#460967
1#
1/
1I
0K
b0 P
1Q
0R
1T
b1 V

#468750
1"
b0 $
b10 )
1.
b0 0
b0 8
1=
b0 @
b11111111 D

#468780
0#
0/

#476593
1#
1/
0I
b1 P
b10 V

#484406
0#
0/

#492219
1#
1/
1J
b10 P
b11 V

#500000
0"
0.
0=

#500032
0#
0/

#507845
1#
1/
0J
b11 P
0U

#515658
0#
0/

#523471
1#
1/
1I
1K
b0 P
0Q
1R
0T
b0 V

#531250
1"
b10000001 $
b11 )
1.
b10000001 0
b1111111 8
1=
b1111111 @
b11111111 D

#531284
0#
0/

#539097
1#
1/
0I
0K
b1 P
b10 Z

#546910
0#
0/

#554723
1#
1/
1J
b10 P

#562500
0"
0.
0=

#562536
0#
0/

#570349
1#
1/
0J
b11 P

#578162
0#
0/

#585975
1#
1/
1I
1K
b0 P

#593750
1"
b0 $
b100 )
1.
b0 0
b0 8
1=
b0 @
b11111111 D

#593788
0#
0/

#601601
1#
1/
0I
0K
b1 P
b11 Z

#609414
0#
0/

#617227
1#
1/
1J
b10 P

#625000
0"
0.
0=

#625040
0#
0/

#632853
1#
1/
0J
b11 P

#640666
0#
0/

#648479
1#
1/
1I
1K
b0 P

#656250
1"
b1111111 $
b101 )
1.
b1111111 0
b1111111 8
1=
b1111111 @
b11111111 D

#656292
0#
0/

#664105
1#
1/
0I
0K
b1 P
b100 Z

#671918
0#
0/

#679731
1#
1/
04
1F
1J
b10 P
0[
1\

#687500
0"
0.
0=

#687544
0#
0/

#695357
1#
1%
1&
1/
05
16
17
0J
b11 P

#703170
0#
0/

#710983
1#
0&
1/
07
1I
1K
b0 P

#718750
1"
b0 $
b110 )
1.
b0 0
b0 8
1=
b0 @
b11111111 D

#718796
0#
0/

#726609
1#
1/
0I
0K
b1 P
b101 Z

#734422
0#
0/

#742235
1#
1/
1J
b10 P

#750000
0"
0.
0=

#750048
0#
0/

#757861
1#
1/
0J
b11 P

#765674
0#
0/

#773487
1#
1/
1I
1K
b0 P

#781250
1"
b10000001 $
b111 )
1.
b10000001 0
b1111111 8
1=
b1111111 @
b11111111 D

#781300
0#
0/

#789113
1#
1/
0I
0K
b1 P
b110 Z

#796926
0#
0/

#804739
1#
1/
1J
b10 P

#812500
0"
0.
0=

#812552
0#
0/

#820365
1#
1/
0J
b11 P

#828178
0#
0/

#835991
1#
1/
1I
1K
b0 P

#843750
1"
b0 $
b1000 )
1.
b0 0
b0 8
1=
b0 @
b11111111 D

#843804
0#
0/

#851617
1#
1/
0I
0K
b1 P
b111 Z

#859430
0#
0/

#867243
1#
1/
1J
b10 P

#875000
0"
0.
0=

#875056
0#
0/

#882869
1#
1/
0J
b11 P

#890682
0#
0/

#898495
1#
1/
1I
1K
b0 P

#906250
1"
b1111111 $
b1001 )
1.
b1111111 0
b1111111 8
1=
b1111111 @
b11111111 D

#906308
0#
0/

#914121
1#
1/
0I
0K
b1 P
b1000 Z

#921934
0#
0/

#929747
1#
1/
14
0F
1J
b10 P
1[
0\

#937500
0"
0.
0=

#937560
0#
0/

#945373
1#
1/
15
0J
b11 P

#953186
0#
0/

#960999
1#
1/
1I
1K
b0 P

#968750
1"
b0 $
b1010 )
1.
b0 0
b0 8
1=
b0 @
b11111111 D

#968812
0#
0/

#976625
1#
1/
0I
0K
b1 P
b1001 Z

#984438
0#
0/

#992251
1#
1/
1J
b10 P

#1000000
0"
0.
0=

#1000064
0#
0/

#1007877
1#
1/
0J
b11 P

#1015690
0#
0/

#1023503
1#
1/
1I
1K
b0 P

#1031250
1"
b10000001 $
b1011 )
1.
b10000001 0
b1111111 8
1=
b1111111 @
b11111111 D

#1031316
0#
0/

#1039129
1#
1/
0I
0K
b1 P
b1010 Z

#1046942
0#
0/

#1054755
1#
1/
1J
b10 P

#1062500
0"
0.
0=

#1062568
0#
0/

#1070381
1#
1/
0J
b11 P

#1078194
0#
0/

#1086007
1#
1/
1I
1K
b0 P

#1093750
1"
b0 $
b1100 )
1.
b0 0
b0 8
1=
b0 @
b11111111 D

#1093820
0#
0/

#1101633
1#
1/
0I
0K
b1 P
b1011 Z

#1109446
0#
0/

#1117259
1#
1/
1J
b10 P

#1125000
0"
0.
0=

#1125072
0#
0/

#1132885
1#
1/
0J
b11 P

#1140698
0#
0/

#1148511
1#
1/
1I
1K
b0 P

#1156250
1"
b1111111 $
b1101 )
1.
b1111111 0
b1111111 8
1=
b1111111 @
b11111111 D

#1156324
0#
0/

#1164137
1#
1/
0I
0K
b1 P
b1100 Z

#1171950
0#
0/

#1179763
1#
1/
04
1F
1J
b10 P
0[
1\

#1187500
0"
0.
0=

#1187576
0#
0/

#1195389
1#
1&
1/
05
17
0J
b11 P

#1203202
0#
0/

#1211015
1#
0&
1/
07
1I
1K
b0 P

#1218750
1"
b0 $
b1110 )
1.
b0 0
b0 8
1=
b0 @
b11111111 D

#1218828
0#
0/

#1226641
1#
1/
0I
0K
b1 P
b1101 Z

#1234454
0#
0/

#1242267
1#
1/
1J
b10 P

#1250000
0"
0.
0=

#1250080
0#
0/

#1257893
1#
1/
0J
b11 P

#1265706
0#
0/

#1273519
1#
1/
1I
1K
b0 P

#1281250
1"
b10000001 $
b1111 )
1.
b10000001 0
b1111111 8
1=
b1111111 @
b11111111 D

#1281332
0#
0/

#1289145
1#
1/
0I
0K
b1 P
b1110 Z

#1296958
0#
0/

#1304771
1#
1/
1J
b10 P

#1312500
0"
0.
0=

#1312584
0#
0/

#1320397
1#
1/
0J
b11 P

#1328210
0#
0/

#1336023
1#
1/
1I
1K
b0 P

#1343750
1"
b0 $
b10000 )
1.
b0 0
b0 8
1=
b0 @
b11111111 D

#1343836
0#
0/

#1351649
1#
1/
0I
0K
b1 P
b1111 Z

#1359462
0#
0/

#1367275
1#
1/
1J
b10 P

#1375000
0"
0.
0=

#1375088
0#
0/

#1382901
1#
1/
0J
b11 P

#1390714
0#
0/

#1398527
1#
1/
1I
1K
b0 P

#1406250
1"
b1111111 $
b10001 )
1.
b1111111 0
b1111111 8
1=
b1111111 @
b11111111 D

#1406340
0#
0/

#1414153
1#
1/
0I
0K
b1 P
b0 Z

#1421966
0#
0/

#1429779
1#
1/
14
0F
1J
b10 P
1[
0\

#1437500
0"
0.
0=

#1437592
0#
0/

#1445405
1#
1/
15
0J
b11 P

#1453218
0#
0/

#1461031
1#
1/
1I
1K
b0 P

#1468750
1"
b0 $
b10010 )
1.
b0 0
b0 8
1=
b0 @
b11111111 D

#1468844
0#
0/

